firebase_orm/__init__.py
firebase_orm/exeptions.py
firebase_orm/models/__init__.py
firebase_orm/models/base.py
firebase_orm/models/manager.py
firebase_orm/models/fields/__init__.py
firebase_orm-0.1.0.dist-info/DESCRIPTION.rst
firebase_orm-0.1.0.dist-info/METADATA
firebase_orm-0.1.0.dist-info/RECORD
firebase_orm-0.1.0.dist-info/WHEEL
firebase_orm-0.1.0.dist-info/metadata.json
firebase_orm-0.1.0.dist-info/top_level.txt
