Metadata-Version: 2.0
Name: firebase-orm
Version: 0.1.0
Summary: NoSQL object model database
Home-page: https://github.com/zavx0z/firebase_orm
Author: Vladimir Filipenko
Author-email: zavx0z@ya.ru
License: MIT
Platform: UNKNOWN
Requires-Dist: firebase-admin (>=2.9.0)
Requires-Dist: grpcio (>=1.9.1)
